{
    "avg": {
        "wmc": 3.73,
        "ccn": 2.78,
        "bugs": 0.06,
        "kanDefect": 0.27,
        "relativeSystemComplexity": 27.24,
        "relativeDataComplexity": 1.42,
        "relativeStructuralComplexity": 25.82,
        "volume": 184.14,
        "commentWeight": 38.24,
        "intelligentContent": 36.58,
        "lcom": 0.93,
        "instability": 0.53,
        "afferentCoupling": 0.95,
        "efferentCoupling": 2.03,
        "difficulty": 5.18,
        "mi": 103.04,
        "distance": 0.33,
        "incomingCDep": 4.6,
        "incomingPDep": 1.4,
        "outgoingCDep": 4.8,
        "outgoingPDep": 2.8,
        "classesPerPackage": 10.4
    },
    "sum": {
        "loc": 5771,
        "cloc": 2198,
        "lloc": 3581,
        "nbMethods": 299,
        "nbClasses": 153,
        "nbInterfaces": 3,
        "nbPackages": 15,
        "violations": {
            "total": 10,
            "information": 0,
            "warning": 10,
            "error": 0,
            "critical": 0
        }
    }
}