{
    "avg": {
        "wmc": 5.37,
        "ccn": 3.1,
        "bugs": 0.09,
        "kanDefect": 0.34,
        "relativeSystemComplexity": 39.66,
        "relativeDataComplexity": 1.08,
        "relativeStructuralComplexity": 38.59,
        "volume": 259.32,
        "commentWeight": 41.29,
        "intelligentContent": 43.39,
        "lcom": 1.44,
        "instability": 0.59,
        "afferentCoupling": 1.32,
        "efferentCoupling": 2.2,
        "difficulty": 5.38,
        "mi": 110.6,
        "distance": 0.29,
        "incomingCDep": 2.33,
        "incomingPDep": 1.44,
        "outgoingCDep": 4.22,
        "outgoingPDep": 2.89,
        "classesPerPackage": 4.78
    },
    "sum": {
        "loc": 2381,
        "cloc": 1045,
        "lloc": 1339,
        "nbMethods": 134,
        "nbClasses": 41,
        "nbInterfaces": 2,
        "nbPackages": 9,
        "violations": {
            "total": 6,
            "information": 0,
            "warning": 6,
            "error": 0,
            "critical": 0
        }
    }
}