{
    "avg": {
        "wmc": 3.63,
        "ccn": 2.7,
        "bugs": 0.06,
        "kanDefect": 0.27,
        "relativeSystemComplexity": 25.44,
        "relativeDataComplexity": 1.4,
        "relativeStructuralComplexity": 24.04,
        "volume": 176.31,
        "commentWeight": 38.04,
        "intelligentContent": 36.15,
        "lcom": 0.93,
        "instability": 0.53,
        "afferentCoupling": 0.93,
        "efferentCoupling": 1.99,
        "difficulty": 5.04,
        "mi": 102.67,
        "distance": 0.33,
        "incomingCDep": 5.33,
        "incomingPDep": 1.4,
        "outgoingCDep": 4.8,
        "outgoingPDep": 2.8,
        "classesPerPackage": 10.87
    },
    "sum": {
        "loc": 5863,
        "cloc": 2195,
        "lloc": 3675,
        "nbMethods": 308,
        "nbClasses": 160,
        "nbInterfaces": 3,
        "nbPackages": 15,
        "violations": {
            "total": 11,
            "information": 0,
            "warning": 11,
            "error": 0,
            "critical": 0
        }
    }
}